htbcli/__init__.py
htbcli/__main__.py
htbcli-1.1.7.dist-info/LICENSE
htbcli-1.1.7.dist-info/METADATA
htbcli-1.1.7.dist-info/WHEEL
htbcli-1.1.7.dist-info/entry_points.txt
htbcli-1.1.7.dist-info/top_level.txt
htbcli-1.1.7.dist-info/RECORD
