Metadata-Version: 2.1
Name: htbcli
Version: 1.1.7
Summary: Hack the Box CLI
Home-page: https://github.com/zachhanson94/htbcli
Author: Zach Hanson
Author-email: zachhanson94@gmail.com
License: ISC
Keywords: hackthebox
Platform: UNKNOWN
Classifier: Development Status :: 3 - Alpha
Classifier: License :: OSI Approved :: ISC License (ISCL)
Classifier: Programming Language :: Python :: 3.7
Requires-Dist: requests
Requires-Dist: argparse
Requires-Dist: tabulate
Requires-Dist: htb
